unconcealed/__init__.py
unconcealed/prep.py
unconcealed/tools.py
unconcealed/widgets.py
unconcealed-0.4.1.dist-info/LICENSE
unconcealed-0.4.1.dist-info/METADATA
unconcealed-0.4.1.dist-info/WHEEL
unconcealed-0.4.1.dist-info/top_level.txt
unconcealed-0.4.1.dist-info/RECORD
